cloudos_webdav_server/__init__.py
cloudos_webdav_server/cloudosDomainController.py
cloudos_webdav_server/clitools/__init__.py
cloudos_webdav_server/clitools/cli.py
cloudos_webdav_server/data/wsgidav_config.yaml
cloudos_webdav_server/data/htdocs/template.html
cloudos_webdav_server/data/htdocs/assets/favicon.ico
cloudos_webdav_server/data/htdocs/assets/logo.png
cloudos_webdav_server/data/htdocs/assets/script.js
cloudos_webdav_server/data/htdocs/assets/style.css
cloudos_webdav_server/services/__init__.py
cloudos_webdav_server/services/file_watcher.py
cloudos_webdav_server/services/realm_access_service.py
cloudos_webdav_server/wsgidav/__init__.py
cloudos_webdav_server/wsgidav/dav_error.py
cloudos_webdav_server/wsgidav/dav_provider.py
cloudos_webdav_server/wsgidav/default_conf.py
cloudos_webdav_server/wsgidav/error_printer.py
cloudos_webdav_server/wsgidav/fs_dav_provider.py
cloudos_webdav_server/wsgidav/http_authenticator.py
cloudos_webdav_server/wsgidav/request_resolver.py
cloudos_webdav_server/wsgidav/request_server.py
cloudos_webdav_server/wsgidav/rw_lock.py
cloudos_webdav_server/wsgidav/stream_tools.py
cloudos_webdav_server/wsgidav/util.py
cloudos_webdav_server/wsgidav/wsgidav_app.py
cloudos_webdav_server/wsgidav/xml_tools.py
cloudos_webdav_server/wsgidav/dc/__init__.py
cloudos_webdav_server/wsgidav/dc/base_dc.py
cloudos_webdav_server/wsgidav/dc/nt_dc.py
cloudos_webdav_server/wsgidav/dc/pam_dc.py
cloudos_webdav_server/wsgidav/dc/simple_dc.py
cloudos_webdav_server/wsgidav/dir_browser/__init__.py
cloudos_webdav_server/wsgidav/dir_browser/_dir_browser.py
cloudos_webdav_server/wsgidav/interfaces/__init__.py
cloudos_webdav_server/wsgidav/interfaces/dav_provider_interface.py
cloudos_webdav_server/wsgidav/interfaces/domaincontrollerinterface.py
cloudos_webdav_server/wsgidav/interfaces/lockmanagerinterface.py
cloudos_webdav_server/wsgidav/interfaces/propertymanagerinterface.py
cloudos_webdav_server/wsgidav/lock_man/__init__.py
cloudos_webdav_server-0.0.0.8.dist-info/METADATA
cloudos_webdav_server-0.0.0.8.dist-info/WHEEL
cloudos_webdav_server-0.0.0.8.dist-info/entry_points.txt
cloudos_webdav_server-0.0.0.8.dist-info/top_level.txt
cloudos_webdav_server-0.0.0.8.dist-info/RECORD
