Metadata-Version: 2.1
Name: cloudos-webdav-server
Version: 0.0.0.8
Summary: Webdav server for cloudos
Home-page: UNKNOWN
Author: Wang Pei
Author-email: 
License: UNKNOWN
Platform: UNKNOWN
Classifier: Programming Language :: Python :: 3
Classifier: License :: OSI Approved :: MIT License
Classifier: Operating System :: OS Independent
Requires-Python: >=3.5
Requires-Dist: fire
Requires-Dist: wsgidav
Requires-Dist: sqlitedict
Requires-Dist: watchdog
